odoo/addons/product_packaging_level_salable/README.rst
odoo/addons/product_packaging_level_salable/__init__.py
odoo/addons/product_packaging_level_salable/__manifest__.py
odoo/addons/product_packaging_level_salable/i18n/es.po
odoo/addons/product_packaging_level_salable/i18n/it.po
odoo/addons/product_packaging_level_salable/i18n/product_packaging_level_salable.pot
odoo/addons/product_packaging_level_salable/models/__init__.py
odoo/addons/product_packaging_level_salable/models/product_packaging.py
odoo/addons/product_packaging_level_salable/models/product_packaging_level.py
odoo/addons/product_packaging_level_salable/models/sale_order_line.py
odoo/addons/product_packaging_level_salable/readme/CONFIGURE.md
odoo/addons/product_packaging_level_salable/readme/CONTRIBUTORS.md
odoo/addons/product_packaging_level_salable/readme/CREDITS.md
odoo/addons/product_packaging_level_salable/readme/DESCRIPTION.md
odoo/addons/product_packaging_level_salable/static/description/icon.png
odoo/addons/product_packaging_level_salable/static/description/index.html
odoo/addons/product_packaging_level_salable/tests/__init__.py
odoo/addons/product_packaging_level_salable/tests/common.py
odoo/addons/product_packaging_level_salable/tests/test_packaging_level_can_be_sold.py
odoo/addons/product_packaging_level_salable/views/product_packaging_level.xml
odoo_addon_product_packaging_level_salable-18.0.1.0.1.1.dist-info/METADATA
odoo_addon_product_packaging_level_salable-18.0.1.0.1.1.dist-info/WHEEL
odoo_addon_product_packaging_level_salable-18.0.1.0.1.1.dist-info/top_level.txt
odoo_addon_product_packaging_level_salable-18.0.1.0.1.1.dist-info/RECORD
